xdol/__init__.py
xdol/paths.py
xdol/pystores.py
xdol/updating.py
xdol/util.py
xdol/x_codecs.py
xdol-0.1.10.dist-info/LICENSE
xdol-0.1.10.dist-info/METADATA
xdol-0.1.10.dist-info/WHEEL
xdol-0.1.10.dist-info/top_level.txt
xdol-0.1.10.dist-info/RECORD
