Metadata-Version: 2.1
Name: xdol
Version: 0.1.10
Summary: Extended Data Object Layers - dol-based tools
License: apache-2.0
License-File: LICENSE
